Metadata-Version: 1.1
Name: ezpy
Version: 0.1.0.dev0
Summary: Make Python application installs easy as pie, for both users and developers
Home-page: https://github.com/jhermann/ezpy
Author: Jürgen Hermann
Author-email: jh@web.de
License: Apache 2.0
Keywords: install,deploy,pip,packaging,virtualenv,hosted.by.github
Platform: UNKNOWN
Classifier: Development Status :: 3 - Alpha
Classifier: Programming Language :: Python :: 3 :: Only
Classifier: Programming Language :: Python :: 3.4
Classifier: Environment :: Console
Classifier: Intended Audience :: End Users/Desktop
Classifier: Intended Audience :: Developers
Classifier: Intended Audience :: Information Technology
Classifier: Intended Audience :: System Administrators
Classifier: License :: OSI Approved :: Apache Software License
Classifier: Operating System :: OS Independent
Classifier: Topic :: Software Development
Classifier: Topic :: System :: Installation/Setup
Classifier: Topic :: System :: Software Distribution
Classifier: Topic :: Utilities
